pipfile_sort
