Metadata-Version: 2.1
Name: pipfile-sort
Version: 0.2.2
Summary: Sort package dependency lists in Pipfile.
Home-page: http://github.com/msh5/pipfile-sort
Author: Sho Minagawa
Author-email: msh5.global@gmail.com
License: MIT
Platform: UNKNOWN
License-File: LICENSE
